{
  "year": "1541",
  "Argentina": [
    "Santa María del Buen Ayre settlement abandoned after indigenous attacks\n"
  ],
  "Barbados": [
    "Spanish commentator Alonza de Santa Cruz speaks of inhabitants of Barbados in the past-tense.\n"
  ],
  "Burma": [
    "Toungoo forces capture Martaban\n"
  ],
  "Chile": [
    "Pedro de Valdivia founds Santiago de Nueva Extremadura, now known as Santiago.\n",
    "es:Lucas Martínez Vegaso founds Villa San Marcos de Arica, now known as Arica.\n",
    "An uprising led by toqui Michimalonco attacks fledgling Santiago in an attempt to drive out the Spanish. Key actions undertaken by Inés de Suárez, the first Spanish woman to set foot in Chile, are attributed with avoiding the complete destruction of the outnumbered settlement.\n"
  ],
  "Colombia": [
    "Jerónimo Luis Tejelo discovers the Aburrá Valley\n"
  ]
}